whop_api_wrapper/Client.py
whop_api_wrapper/Endpoints.py
whop_api_wrapper/Objects.py
whop_api_wrapper/__init__.py
whop_api_wrapper-1.1.8.dist-info/licenses/LICENSE
whop_api_wrapper-1.1.8.dist-info/METADATA
whop_api_wrapper-1.1.8.dist-info/WHEEL
whop_api_wrapper-1.1.8.dist-info/top_level.txt
whop_api_wrapper-1.1.8.dist-info/RECORD
