Metadata-Version: 2.4
Name: whop-api-wrapper
Version: 1.1.8
Summary: Simple Python Whop API Wrapper
Home-page: https://github.com/TheSweeet/Whop-API-Wrapper
Author: Jacobfinn123
Author-email: jacobfinn@bezosproxy.com
Keywords: WHOP,API,WRAPPER
Classifier: Development Status :: 5 - Production/Stable
Classifier: Intended Audience :: Developers
Classifier: License :: OSI Approved :: MIT License
Classifier: Programming Language :: Python :: 3
Classifier: Programming Language :: Python :: 3.6
Classifier: Programming Language :: Python :: 3.7
Classifier: Programming Language :: Python :: 3.8
Classifier: Programming Language :: Python :: 3.9
License-File: LICENSE
Requires-Dist: requests
Dynamic: author
Dynamic: author-email
Dynamic: classifier
Dynamic: description
Dynamic: description-content-type
Dynamic: home-page
Dynamic: keywords
Dynamic: license-file
Dynamic: requires-dist
Dynamic: summary
